MANIFEST.in
README.rst
setup.py
python_subreg.egg-info/PKG-INFO
python_subreg.egg-info/SOURCES.txt
python_subreg.egg-info/dependency_links.txt
python_subreg.egg-info/not-zip-safe
python_subreg.egg-info/requires.txt
python_subreg.egg-info/top_level.txt
subreg/__init__.py
subreg/api.py
subreg/exceptions.py
subreg/tests.py