Metadata-Version: 1.1
Name: python-subreg
Version: 0.0.6
Summary: Python wrapper around the subreg.cz SOAP API
Home-page: http://github.com/cikorka/python-subreg
Author: Petr Jerabek
Author-email: cikorka@me.com
License: MIT
Keywords: subreg subreg.cz
Platform: UNKNOWN
Classifier: Development Status :: 3 - Alpha
Classifier: License :: OSI Approved :: MIT License
